deepmind/__init__.py
deepmind/cfd.py
deepmind/machine_learning.py
deepmind/main.py
deepmind/parameters.py
deepmind/preprocessing.py
deepmind/test.py
deepmind/tools.py
deepmind-0.0.1.dist-info/LICENSE
deepmind-0.0.1.dist-info/METADATA
deepmind-0.0.1.dist-info/WHEEL
deepmind-0.0.1.dist-info/top_level.txt
deepmind-0.0.1.dist-info/RECORD
